pynovice/__init__.py
pynovice/bert_extracter/__init__.py
pynovice/bert_extracter/bert_extracter.py
pynovice/echarts_plot/__init__.py
pynovice/echarts_plot/anysis_distribution_plot.py
pynovice/echarts_plot/anysis_distribution_plot_v2.py
pynovice/echarts_plot/echarts_base_plot.py
pynovice/gaode_map/__init__.py
pynovice/gaode_map/pynovice_map.js
pynovice/gaode_map/trajectory_playback.py
pynovice/gaode_map/trajectory_playback_v2.py
pynovice/geo_map/.DS_Store
pynovice/geo_map/CITY.cg
pynovice/geo_map/__init__.py
pynovice/geo_map/geo_map.py
pynovice/geo_map/google_map.py
pynovice/geo_map/requirements.txt
pynovice/knowledge_notes/__init__.py
pynovice/knowledge_notes/怎么自定义jupyter的magic命令.py
pynovice/rule_engine/__init__.py
pynovice/rule_engine/rule_parser.py
pynovice/score_card/__init__.py
pynovice/score_card/feature_preprocessing.py
pynovice/score_card/model_base.py
pynovice/score_card/model_logistic.py
pynovice/score_card/model_xgboost.py
pynovice/score_card/model_rf_lr/__init__.py
pynovice/score_card/model_rf_lr/features.py
pynovice/score_card/model_rf_lr/randomforest_blocks.py
pynovice/score_card/model_rf_lr/run.py
pynovice/score_card/model_rf_lr/woe.py
pynovice/score_card/src/__init__.py
pynovice/score_card/src/category_coder.py
pynovice/score_card/src/data_binning.py
pynovice/score_card/src/data_woe.py
pynovice/score_card/src/g7_score_card.py
pynovice/score_card/src/g7_woe.py
pynovice/score_card/src/psi_csi.py
pynovice/score_card/src/score_card.py
pynovice/score_card/src/card_explanations/__init__.py
pynovice/score_card/src/card_explanations/_beeswarm.py
pynovice/score_card/src/card_explanations/_force.py
pynovice/score_card/src/card_explanations/_waterfall.py
pynovice/score_card/src/card_explanations/utils/__init__.py
pynovice/score_card/src/card_explanations/utils/_colorconv.py
pynovice/score_card/src/card_explanations/utils/_colors.py
pynovice/score_card/src/card_explanations/utils/_explanation.py
pynovice-0.2.72.dist-info/DESCRIPTION.rst
pynovice-0.2.72.dist-info/METADATA
pynovice-0.2.72.dist-info/RECORD
pynovice-0.2.72.dist-info/WHEEL
pynovice-0.2.72.dist-info/metadata.json
pynovice-0.2.72.dist-info/top_level.txt
