Metadata-Version: 2.0
Name: pynovice
Version: 0.2.72
Summary: data mining for novice and expert
Home-page: https://github.com/wqwangchn/novice
Author: wqwangchn
Author-email: wqwangchn@163.com
License: UNKNOWN
Platform: UNKNOWN
Classifier: Programming Language :: Python :: 3
Classifier: License :: OSI Approved :: MIT License
Classifier: Operating System :: OS Independent
Requires-Dist: numpy
Requires-Dist: pandas
Requires-Dist: scipy
